sqlcipher4/__init__.py
sqlcipher4/__init__.pyi
sqlcipher4/dbapi2.py
sqlcipher4/dbapi2.pyi
sqlcipher4/py.typed
sqlcipher4/sqlite3.c
sqlcipher4/sqlite3.h
bouquin_sqlcipher4-4.12.0.dist-info/LICENSE
bouquin_sqlcipher4-4.12.0.dist-info/METADATA
bouquin_sqlcipher4-4.12.0.dist-info/WHEEL
bouquin_sqlcipher4-4.12.0.dist-info/RECORD
