Metadata-Version: 2.1
Name: bouquin-sqlcipher4
Version: 4.12.0
Summary: DB-API 2.0 interface for SQLCipher 4.x, for use with Bouquin
Home-page: https://git.mig5.net/mig5/bouquin-sqlcipher4
License: MIT
Author: Miguel Jacq
Author-email: mig@mig5.net
Requires-Python: >=3.10,<4.0
Classifier: License :: OSI Approved :: MIT License
Classifier: Programming Language :: Python :: 3
Classifier: Programming Language :: Python :: 3.10
Classifier: Programming Language :: Python :: 3.11
Classifier: Programming Language :: Python :: 3.12
Project-URL: Repository, https://git.mig5.net/mig5/bouquin-sqlcipher4
